{"sentences":[{"index":0,"tokens":[{"index":1,"word":"From","originalText":"From","characterOffsetBegin":0,"characterOffsetEnd":4,"pos":"IN","before":"","after":""},{"index":2,"word":":","originalText":":","characterOffsetBegin":4,"characterOffsetEnd":5,"pos":":","before":"","after":" "},{"index":3,"word":"segal@rtsg.mot.com","originalText":"segal@rtsg.mot.com","characterOffsetBegin":6,"characterOffsetEnd":24,"pos":"NN","before":" ","after":" "},{"index":4,"word":"-LRB-","originalText":"(","characterOffsetBegin":25,"characterOffsetEnd":26,"pos":"-LRB-","before":" ","after":""},{"index":5,"word":"Gary","originalText":"Gary","characterOffsetBegin":26,"characterOffsetEnd":30,"pos":"NNP","before":"","after":" "},{"index":6,"word":"Segal","originalText":"Segal","characterOffsetBegin":31,"characterOffsetEnd":36,"pos":"NNP","before":" ","after":""},{"index":7,"word":"-RRB-","originalText":")","characterOffsetBegin":36,"characterOffsetEnd":37,"pos":"-RRB-","before":"","after":""},{"index":8,"word":"Subject","originalText":"Subject","characterOffsetBegin":37,"characterOffsetEnd":44,"pos":"NNP","before":"","after":""},{"index":9,"word":":","originalText":":","characterOffsetBegin":44,"characterOffsetEnd":45,"pos":":","before":"","after":" "},{"index":10,"word":"Pinout","originalText":"Pinout","characterOffsetBegin":46,"characterOffsetEnd":52,"pos":"NNP","before":" ","after":" "},{"index":11,"word":"needed","originalText":"needed","characterOffsetBegin":53,"characterOffsetEnd":59,"pos":"VBD","before":" ","after":" "},{"index":12,"word":"for","originalText":"for","characterOffsetBegin":60,"characterOffsetEnd":63,"pos":"IN","before":" ","after":" "},{"index":13,"word":"TIL311I","originalText":"TIL311I","characterOffsetBegin":64,"characterOffsetEnd":71,"pos":"NN","before":" ","after":""},{"index":14,"word":"'ve","originalText":"'ve","characterOffsetBegin":71,"characterOffsetEnd":74,"pos":"VBP","before":"","after":" "},{"index":15,"word":"recently","originalText":"recently","characterOffsetBegin":75,"characterOffsetEnd":83,"pos":"RB","before":" ","after":" "},{"index":16,"word":"picked","originalText":"picked","characterOffsetBegin":84,"characterOffsetEnd":90,"pos":"VBN","before":" ","after":" "},{"index":17,"word":"up","originalText":"up","characterOffsetBegin":91,"characterOffsetEnd":93,"pos":"RP","before":" ","after":" "},{"index":18,"word":"some","originalText":"some","characterOffsetBegin":94,"characterOffsetEnd":98,"pos":"DT","before":" ","after":" "},{"index":19,"word":"TIL311","originalText":"TIL311","characterOffsetBegin":99,"characterOffsetEnd":105,"pos":"NN","before":" ","after":" "},{"index":20,"word":"display","originalText":"display","characterOffsetBegin":106,"characterOffsetEnd":113,"pos":"NN","before":" ","after":" "},{"index":21,"word":"chips","originalText":"chips","characterOffsetBegin":114,"characterOffsetEnd":119,"pos":"NNS","before":" ","after":""},{"index":22,"word":",","originalText":",","characterOffsetBegin":119,"characterOffsetEnd":120,"pos":",","before":"","after":" "},{"index":23,"word":"but","originalText":"but","characterOffsetBegin":121,"characterOffsetEnd":124,"pos":"CC","before":" ","after":" "},{"index":24,"word":"I","originalText":"I","characterOffsetBegin":125,"characterOffsetEnd":126,"pos":"PRP","before":" ","after":" "},{"index":25,"word":"ca","originalText":"ca","characterOffsetBegin":127,"characterOffsetEnd":129,"pos":"MD","before":" ","after":""},{"index":26,"word":"n't","originalText":"n't","characterOffsetBegin":129,"characterOffsetEnd":132,"pos":"RB","before":"","after":" "},{"index":27,"word":"findany","originalText":"findany","characterOffsetBegin":133,"characterOffsetEnd":140,"pos":"VB","before":" ","after":" "},{"index":28,"word":"information","originalText":"information","characterOffsetBegin":141,"characterOffsetEnd":152,"pos":"NN","before":" ","after":" "},{"index":29,"word":"on","originalText":"on","characterOffsetBegin":153,"characterOffsetEnd":155,"pos":"IN","before":" ","after":" "},{"index":30,"word":"them","originalText":"them","characterOffsetBegin":156,"characterOffsetEnd":160,"pos":"PRP","before":" ","after":""},{"index":31,"word":".","originalText":".","characterOffsetBegin":160,"characterOffsetEnd":161,"pos":".","before":"","after":"  "}]},{"index":1,"tokens":[{"index":1,"word":"It","originalText":"It","characterOffsetBegin":163,"characterOffsetEnd":165,"pos":"PRP","before":"  ","after":" "},{"index":2,"word":"seems","originalText":"seems","characterOffsetBegin":166,"characterOffsetEnd":171,"pos":"VBZ","before":" ","after":" "},{"index":3,"word":"they","originalText":"they","characterOffsetBegin":172,"characterOffsetEnd":176,"pos":"PRP","before":" ","after":" "},{"index":4,"word":"are","originalText":"are","characterOffsetBegin":177,"characterOffsetEnd":180,"pos":"VBP","before":" ","after":" "},{"index":5,"word":"no","originalText":"no","characterOffsetBegin":181,"characterOffsetEnd":183,"pos":"RB","before":" ","after":" "},{"index":6,"word":"longer","originalText":"longer","characterOffsetBegin":184,"characterOffsetEnd":190,"pos":"RBR","before":" ","after":" "},{"index":7,"word":"made","originalText":"made","characterOffsetBegin":191,"characterOffsetEnd":195,"pos":"VBN","before":" ","after":" "},{"index":8,"word":"by","originalText":"by","characterOffsetBegin":196,"characterOffsetEnd":198,"pos":"IN","before":" ","after":" "},{"index":9,"word":"TI","originalText":"TI","characterOffsetBegin":199,"characterOffsetEnd":201,"pos":"NNP","before":" ","after":""},{"index":10,"word":",","originalText":",","characterOffsetBegin":201,"characterOffsetEnd":202,"pos":",","before":"","after":" "},{"index":11,"word":"andI","originalText":"andI","characterOffsetBegin":203,"characterOffsetEnd":207,"pos":"NNP","before":" ","after":" "},{"index":12,"word":"do","originalText":"do","characterOffsetBegin":208,"characterOffsetEnd":210,"pos":"VBP","before":" ","after":""},{"index":13,"word":"n't","originalText":"n't","characterOffsetBegin":210,"characterOffsetEnd":213,"pos":"RB","before":"","after":" "},{"index":14,"word":"have","originalText":"have","characterOffsetBegin":214,"characterOffsetEnd":218,"pos":"VB","before":" ","after":" "},{"index":15,"word":"an","originalText":"an","characterOffsetBegin":219,"characterOffsetEnd":221,"pos":"DT","before":" ","after":" "},{"index":16,"word":"old","originalText":"old","characterOffsetBegin":222,"characterOffsetEnd":225,"pos":"JJ","before":" ","after":" "},{"index":17,"word":"enough","originalText":"enough","characterOffsetBegin":226,"characterOffsetEnd":232,"pos":"JJ","before":" ","after":" "},{"index":18,"word":"data","originalText":"data","characterOffsetBegin":233,"characterOffsetEnd":237,"pos":"NNS","before":" ","after":" "},{"index":19,"word":"book","originalText":"book","characterOffsetBegin":238,"characterOffsetEnd":242,"pos":"NN","before":" ","after":""},{"index":20,"word":".","originalText":".","characterOffsetBegin":242,"characterOffsetEnd":243,"pos":".","before":"","after":"  "}]},{"index":2,"tokens":[{"index":1,"word":":","originalText":":","characterOffsetBegin":245,"characterOffsetEnd":246,"pos":":","before":"  ","after":""},{"index":2,"word":"-","originalText":"-","characterOffsetBegin":246,"characterOffsetEnd":247,"pos":":","before":"","after":""},{"index":3,"word":"-LRB-","originalText":"(","characterOffsetBegin":247,"characterOffsetEnd":248,"pos":"-LRB-","before":"","after":""},{"index":4,"word":"It","originalText":"It","characterOffsetBegin":248,"characterOffsetEnd":250,"pos":"PRP","before":"","after":" "},{"index":5,"word":"appears","originalText":"appears","characterOffsetBegin":251,"characterOffsetEnd":258,"pos":"VBZ","before":" ","after":" "},{"index":6,"word":"to","originalText":"to","characterOffsetBegin":259,"characterOffsetEnd":261,"pos":"TO","before":" ","after":" "},{"index":7,"word":"have","originalText":"have","characterOffsetBegin":262,"characterOffsetEnd":266,"pos":"VB","before":" ","after":" "},{"index":8,"word":"a","originalText":"a","characterOffsetBegin":267,"characterOffsetEnd":268,"pos":"DT","before":" ","after":" "},{"index":9,"word":"dot-matrix","originalText":"dot-matrix","characterOffsetBegin":269,"characterOffsetEnd":279,"pos":"NN","before":" ","after":" "},{"index":10,"word":"led","originalText":"led","characterOffsetBegin":280,"characterOffsetEnd":283,"pos":"VBD","before":" ","after":" "},{"index":11,"word":"display","originalText":"display","characterOffsetBegin":284,"characterOffsetEnd":291,"pos":"NN","before":" ","after":" "},{"index":12,"word":"capable","originalText":"capable","characterOffsetBegin":292,"characterOffsetEnd":299,"pos":"JJ","before":" ","after":" "},{"index":13,"word":"of","originalText":"of","characterOffsetBegin":300,"characterOffsetEnd":302,"pos":"IN","before":" ","after":" "},{"index":14,"word":"showing","originalText":"showing","characterOffsetBegin":303,"characterOffsetEnd":310,"pos":"VBG","before":" ","after":" "},{"index":15,"word":"one","originalText":"one","characterOffsetBegin":311,"characterOffsetEnd":314,"pos":"CD","before":" ","after":" "},{"index":16,"word":"hexdigit","originalText":"hexdigit","characterOffsetBegin":315,"characterOffsetEnd":323,"pos":"NN","before":" ","after":""},{"index":17,"word":".","originalText":".","characterOffsetBegin":323,"characterOffsetEnd":324,"pos":".","before":"","after":"  "}]},{"index":3,"tokens":[{"index":1,"word":"It","originalText":"It","characterOffsetBegin":326,"characterOffsetEnd":328,"pos":"PRP","before":"  ","after":" "},{"index":2,"word":"is","originalText":"is","characterOffsetBegin":329,"characterOffsetEnd":331,"pos":"VBZ","before":" ","after":" "},{"index":3,"word":"in","originalText":"in","characterOffsetBegin":332,"characterOffsetEnd":334,"pos":"IN","before":" ","after":" "},{"index":4,"word":"a","originalText":"a","characterOffsetBegin":335,"characterOffsetEnd":336,"pos":"DT","before":" ","after":" "},{"index":5,"word":"14","originalText":"14","characterOffsetBegin":337,"characterOffsetEnd":339,"pos":"CD","before":" ","after":" "},{"index":6,"word":"pin","originalText":"pin","characterOffsetBegin":340,"characterOffsetEnd":343,"pos":"NN","before":" ","after":" "},{"index":7,"word":"DIP","originalText":"DIP","characterOffsetBegin":344,"characterOffsetEnd":347,"pos":"NN","before":" ","after":" "},{"index":8,"word":"package","originalText":"package","characterOffsetBegin":348,"characterOffsetEnd":355,"pos":"NN","before":" ","after":""},{"index":9,"word":",","originalText":",","characterOffsetBegin":355,"characterOffsetEnd":356,"pos":",","before":"","after":" "},{"index":10,"word":"but","originalText":"but","characterOffsetBegin":357,"characterOffsetEnd":360,"pos":"CC","before":" ","after":" "},{"index":11,"word":"pins","originalText":"pins","characterOffsetBegin":361,"characterOffsetEnd":365,"pos":"NNS","before":" ","after":" "},{"index":12,"word":"6","originalText":"6","characterOffsetBegin":366,"characterOffsetEnd":367,"pos":"CD","before":" ","after":""},{"index":13,"word":",","originalText":",","characterOffsetBegin":367,"characterOffsetEnd":368,"pos":",","before":"","after":" "},{"index":14,"word":"9","originalText":"9","characterOffsetBegin":369,"characterOffsetEnd":370,"pos":"CD","before":" ","after":""},{"index":15,"word":",","originalText":",","characterOffsetBegin":370,"characterOffsetEnd":371,"pos":",","before":"","after":" "},{"index":16,"word":"and","originalText":"and","characterOffsetBegin":372,"characterOffsetEnd":375,"pos":"CC","before":" ","after":" "},{"index":17,"word":"11","originalText":"11","characterOffsetBegin":376,"characterOffsetEnd":378,"pos":"CD","before":" ","after":" "},{"index":18,"word":"are","originalText":"are","characterOffsetBegin":379,"characterOffsetEnd":382,"pos":"VBP","before":" ","after":" "},{"index":19,"word":"notpresent.If","originalText":"notpresent.If","characterOffsetBegin":383,"characterOffsetEnd":396,"pos":"NNP","before":" ","after":" "},{"index":20,"word":"you","originalText":"you","characterOffsetBegin":397,"characterOffsetEnd":400,"pos":"PRP","before":" ","after":" "},{"index":21,"word":"have","originalText":"have","characterOffsetBegin":401,"characterOffsetEnd":405,"pos":"VBP","before":" ","after":" "},{"index":22,"word":"any","originalText":"any","characterOffsetBegin":406,"characterOffsetEnd":409,"pos":"DT","before":" ","after":" "},{"index":23,"word":"information","originalText":"information","characterOffsetBegin":410,"characterOffsetEnd":421,"pos":"NN","before":" ","after":" "},{"index":24,"word":"on","originalText":"on","characterOffsetBegin":422,"characterOffsetEnd":424,"pos":"IN","before":" ","after":" "},{"index":25,"word":"this","originalText":"this","characterOffsetBegin":425,"characterOffsetEnd":429,"pos":"DT","before":" ","after":" "},{"index":26,"word":"part","originalText":"part","characterOffsetBegin":430,"characterOffsetEnd":434,"pos":"NN","before":" ","after":" "},{"index":27,"word":"-LRB-","originalText":"(","characterOffsetBegin":435,"characterOffsetEnd":436,"pos":"-LRB-","before":" ","after":""},{"index":28,"word":"pinout","originalText":"pinout","characterOffsetBegin":436,"characterOffsetEnd":442,"pos":"NN","before":"","after":""},{"index":29,"word":",","originalText":",","characterOffsetBegin":442,"characterOffsetEnd":443,"pos":",","before":"","after":" "},{"index":30,"word":"power","originalText":"power","characterOffsetBegin":444,"characterOffsetEnd":449,"pos":"NN","before":" ","after":" "},{"index":31,"word":"requirments","originalText":"requirments","characterOffsetBegin":450,"characterOffsetEnd":461,"pos":"NNS","before":" ","after":""},{"index":32,"word":",","originalText":",","characterOffsetBegin":461,"characterOffsetEnd":462,"pos":",","before":"","after":""},{"index":33,"word":"functions","originalText":"functions","characterOffsetBegin":462,"characterOffsetEnd":471,"pos":"NNS","before":"","after":""},{"index":34,"word":",","originalText":",","characterOffsetBegin":471,"characterOffsetEnd":472,"pos":",","before":"","after":" "},{"index":35,"word":"...","originalText":"...","characterOffsetBegin":473,"characterOffsetEnd":476,"pos":":","before":" ","after":""},{"index":36,"word":"-RRB-","originalText":")","characterOffsetBegin":476,"characterOffsetEnd":477,"pos":"-RRB-","before":"","after":" "},{"index":37,"word":"please","originalText":"please","characterOffsetBegin":478,"characterOffsetEnd":484,"pos":"VB","before":" ","after":" "},{"index":38,"word":"send","originalText":"send","characterOffsetBegin":485,"characterOffsetEnd":489,"pos":"VB","before":" ","after":" "},{"index":39,"word":"me","originalText":"me","characterOffsetBegin":490,"characterOffsetEnd":492,"pos":"PRP","before":" ","after":" "},{"index":40,"word":"e-mail","originalText":"e-mail","characterOffsetBegin":493,"characterOffsetEnd":499,"pos":"VB","before":" ","after":""},{"index":41,"word":".","originalText":".","characterOffsetBegin":499,"characterOffsetEnd":500,"pos":".","before":"","after":""}]},{"index":4,"tokens":[{"index":1,"word":"Thank","originalText":"Thank","characterOffsetBegin":500,"characterOffsetEnd":505,"pos":"VB","before":"","after":" "},{"index":2,"word":"You","originalText":"You","characterOffsetBegin":506,"characterOffsetEnd":509,"pos":"PRP","before":" ","after":""},{"index":3,"word":",","originalText":",","characterOffsetBegin":509,"characterOffsetEnd":510,"pos":",","before":"","after":""},{"index":4,"word":"--","originalText":"--","characterOffsetBegin":510,"characterOffsetEnd":512,"pos":":","before":"","after":" "},{"index":5,"word":"Gary","originalText":"Gary","characterOffsetBegin":513,"characterOffsetEnd":517,"pos":"NNP","before":" ","after":" "},{"index":6,"word":"Segal","originalText":"Segal","characterOffsetBegin":518,"characterOffsetEnd":523,"pos":"NNP","before":" ","after":"                             "},{"index":7,"word":"Motorola","originalText":"Motorola","characterOffsetBegin":552,"characterOffsetEnd":560,"pos":"NNP","before":"                             ","after":" "},{"index":8,"word":"Inc.","originalText":"Inc","characterOffsetBegin":561,"characterOffsetEnd":564,"pos":"NNP","before":" ","after":""},{"index":9,"word":".","originalText":".","characterOffsetBegin":564,"characterOffsetEnd":565,"pos":".","before":"","after":"            "}]},{"index":5,"tokens":[{"index":1,"word":"segal@oscar.rtsg.mot.com","originalText":"segal@oscar.rtsg.mot.com","characterOffsetBegin":577,"characterOffsetEnd":601,"pos":"NNP","before":"            ","after":"               "},{"index":2,"word":"Cellular","originalText":"Cellular","characterOffsetBegin":616,"characterOffsetEnd":624,"pos":"NNP","before":"               ","after":" "},{"index":3,"word":"Infrastructure","originalText":"Infrastructure","characterOffsetBegin":625,"characterOffsetEnd":639,"pos":"NNP","before":" ","after":" "},{"index":4,"word":"Division","originalText":"Division","characterOffsetBegin":640,"characterOffsetEnd":648,"pos":"NNP","before":" ","after":"\t"},{"index":5,"word":"--","originalText":"---","characterOffsetBegin":649,"characterOffsetEnd":652,"pos":":","before":"\t","after":" "},{"index":6,"word":"we","originalText":"we","characterOffsetBegin":653,"characterOffsetEnd":655,"pos":"PRP","before":" ","after":" "},{"index":7,"word":"are","originalText":"are","characterOffsetBegin":656,"characterOffsetEnd":659,"pos":"VBP","before":" ","after":" "},{"index":8,"word":"standing","originalText":"standing","characterOffsetBegin":660,"characterOffsetEnd":668,"pos":"VBG","before":" ","after":" "},{"index":9,"word":"here","originalText":"here","characterOffsetBegin":669,"characterOffsetEnd":673,"pos":"RB","before":" ","after":" "},{"index":10,"word":"only","originalText":"only","characterOffsetBegin":674,"characterOffsetEnd":678,"pos":"RB","before":" ","after":" "},{"index":11,"word":"to","originalText":"to","characterOffsetBegin":679,"characterOffsetEnd":681,"pos":"TO","before":" ","after":" "},{"index":12,"word":"gaze","originalText":"gaze","characterOffsetBegin":682,"characterOffsetEnd":686,"pos":"VB","before":" ","after":" "},{"index":13,"word":"at","originalText":"at","characterOffsetBegin":687,"characterOffsetEnd":689,"pos":"IN","before":" ","after":" "},{"index":14,"word":"the","originalText":"the","characterOffsetBegin":690,"characterOffsetEnd":693,"pos":"DT","before":" ","after":" "},{"index":15,"word":"wind","originalText":"wind","characterOffsetBegin":694,"characterOffsetEnd":698,"pos":"NN","before":" ","after":" "},{"index":16,"word":"--","originalText":"---","characterOffsetBegin":699,"characterOffsetEnd":702,"pos":":","before":" ","after":""}]}]}