{"sentences":[{"index":0,"tokens":[{"index":1,"word":"From","originalText":"From","characterOffsetBegin":0,"characterOffsetEnd":4,"pos":"IN","before":"","after":""},{"index":2,"word":":","originalText":":","characterOffsetBegin":4,"characterOffsetEnd":5,"pos":":","before":"","after":" "},{"index":3,"word":"ggruscho@nyx.cs.du.edu","originalText":"ggruscho@nyx.cs.du.edu","characterOffsetBegin":6,"characterOffsetEnd":28,"pos":"NN","before":" ","after":" "},{"index":4,"word":"-LRB-","originalText":"(","characterOffsetBegin":29,"characterOffsetEnd":30,"pos":"-LRB-","before":" ","after":""},{"index":5,"word":"George","originalText":"George","characterOffsetBegin":30,"characterOffsetEnd":36,"pos":"NNP","before":"","after":" "},{"index":6,"word":"Gruschow","originalText":"Gruschow","characterOffsetBegin":37,"characterOffsetEnd":45,"pos":"NNP","before":" ","after":""},{"index":7,"word":"-RRB-","originalText":")","characterOffsetBegin":45,"characterOffsetEnd":46,"pos":"-RRB-","before":"","after":""},{"index":8,"word":"Subject","originalText":"Subject","characterOffsetBegin":46,"characterOffsetEnd":53,"pos":"NNP","before":"","after":""},{"index":9,"word":":","originalText":":","characterOffsetBegin":53,"characterOffsetEnd":54,"pos":":","before":"","after":" "},{"index":10,"word":"Re","originalText":"Re","characterOffsetBegin":55,"characterOffsetEnd":57,"pos":"NNP","before":" ","after":""},{"index":11,"word":":","originalText":":","characterOffsetBegin":57,"characterOffsetEnd":58,"pos":":","before":"","after":" "},{"index":12,"word":"How","originalText":"How","characterOffsetBegin":59,"characterOffsetEnd":62,"pos":"WRB","before":" ","after":" "},{"index":13,"word":"to","originalText":"to","characterOffsetBegin":63,"characterOffsetEnd":65,"pos":"TO","before":" ","after":" "},{"index":14,"word":"the","originalText":"the","characterOffsetBegin":66,"characterOffsetEnd":69,"pos":"DT","before":" ","after":" "},{"index":15,"word":"disks","originalText":"disks","characterOffsetBegin":70,"characterOffsetEnd":75,"pos":"NNS","before":" ","after":" "},{"index":16,"word":"copy","originalText":"copy","characterOffsetBegin":76,"characterOffsetEnd":80,"pos":"VBP","before":" ","after":" "},{"index":17,"word":"protected.ketil@edb.tih.no","originalText":"protected.ketil@edb.tih.no","characterOffsetBegin":81,"characterOffsetEnd":107,"pos":"NN","before":" ","after":" "},{"index":18,"word":"-LRB-","originalText":"(","characterOffsetBegin":108,"characterOffsetEnd":109,"pos":"-LRB-","before":" ","after":""},{"index":19,"word":"Ketil","originalText":"Ketil","characterOffsetBegin":109,"characterOffsetEnd":114,"pos":"NNP","before":"","after":" "},{"index":20,"word":"Albertsen","originalText":"Albertsen","characterOffsetBegin":115,"characterOffsetEnd":124,"pos":"NNP","before":" ","after":""},{"index":21,"word":",","originalText":",","characterOffsetBegin":124,"characterOffsetEnd":125,"pos":",","before":"","after":""},{"index":22,"word":"TIH","originalText":"TIH","characterOffsetBegin":125,"characterOffsetEnd":128,"pos":"NN","before":"","after":""},{"index":23,"word":"-RRB-","originalText":")","characterOffsetBegin":128,"characterOffsetEnd":129,"pos":"-RRB-","before":"","after":" "},{"index":24,"word":"writes","originalText":"writes","characterOffsetBegin":130,"characterOffsetEnd":136,"pos":"VBZ","before":" ","after":""},{"index":25,"word":":","originalText":":","characterOffsetBegin":136,"characterOffsetEnd":137,"pos":":","before":"","after":""},{"index":26,"word":">","originalText":">","characterOffsetBegin":137,"characterOffsetEnd":138,"pos":"JJR","before":"","after":""},{"index":27,"word":"In","originalText":"In","characterOffsetBegin":138,"characterOffsetEnd":140,"pos":"IN","before":"","after":" "},{"index":28,"word":"article","originalText":"article","characterOffsetBegin":141,"characterOffsetEnd":148,"pos":"NN","before":" ","after":" "},{"index":29,"word":"<1993Apr20.230749.12821@reed.edu>","originalText":"<1993Apr20.230749.12821@reed.edu>","characterOffsetBegin":149,"characterOffsetEnd":182,"pos":"NN","before":" ","after":""},{"index":30,"word":",","originalText":",","characterOffsetBegin":182,"characterOffsetEnd":183,"pos":",","before":"","after":" "},{"index":31,"word":"mblock@reed.edu","originalText":"mblock@reed.edu","characterOffsetBegin":184,"characterOffsetEnd":199,"pos":"NN","before":" ","after":" "},{"index":32,"word":"-LRB-","originalText":"(","characterOffsetBegin":200,"characterOffsetEnd":201,"pos":"-LRB-","before":" ","after":""},{"index":33,"word":"Matt","originalText":"Matt","characterOffsetBegin":201,"characterOffsetEnd":205,"pos":"NNP","before":"","after":" "},{"index":34,"word":"Block","originalText":"Block","characterOffsetBegin":206,"characterOffsetEnd":211,"pos":"NNP","before":" ","after":""},{"index":35,"word":"-RRB-","originalText":")","characterOffsetBegin":211,"characterOffsetEnd":212,"pos":"-RRB-","before":"","after":" "},{"index":36,"word":"writes","originalText":"writes","characterOffsetBegin":213,"characterOffsetEnd":219,"pos":"VBZ","before":" ","after":""},{"index":37,"word":":","originalText":":","characterOffsetBegin":219,"characterOffsetEnd":220,"pos":":","before":"","after":""},{"index":38,"word":">>","originalText":">>","characterOffsetBegin":220,"characterOffsetEnd":222,"pos":"CD","before":"","after":"\t"},{"index":39,"word":"I","originalText":"I","characterOffsetBegin":223,"characterOffsetEnd":224,"pos":"PRP","before":"\t","after":" "},{"index":40,"word":"guess","originalText":"guess","characterOffsetBegin":225,"characterOffsetEnd":230,"pos":"VBP","before":" ","after":" "},{"index":41,"word":"what","originalText":"what","characterOffsetBegin":231,"characterOffsetEnd":235,"pos":"WP","before":" ","after":" "},{"index":42,"word":"I","originalText":"I","characterOffsetBegin":236,"characterOffsetEnd":237,"pos":"PRP","before":" ","after":" "},{"index":43,"word":"am","originalText":"am","characterOffsetBegin":238,"characterOffsetEnd":240,"pos":"VBP","before":" ","after":" "},{"index":44,"word":"saying","originalText":"saying","characterOffsetBegin":241,"characterOffsetEnd":247,"pos":"VBG","before":" ","after":" "},{"index":45,"word":"is","originalText":"is","characterOffsetBegin":248,"characterOffsetEnd":250,"pos":"VBZ","before":" ","after":" "},{"index":46,"word":"that","originalText":"that","characterOffsetBegin":251,"characterOffsetEnd":255,"pos":"IN","before":" ","after":" "},{"index":47,"word":"your","originalText":"your","characterOffsetBegin":256,"characterOffsetEnd":260,"pos":"PRP$","before":" ","after":" "},{"index":48,"word":"question","originalText":"question","characterOffsetBegin":261,"characterOffsetEnd":269,"pos":"NN","before":" ","after":" "},{"index":49,"word":"is","originalText":"is","characterOffsetBegin":270,"characterOffsetEnd":272,"pos":"VBZ","before":" ","after":" "},{"index":50,"word":"difficult","originalText":"difficult","characterOffsetBegin":273,"characterOffsetEnd":282,"pos":"JJ","before":" ","after":""},{"index":51,"word":",","originalText":",","characterOffsetBegin":282,"characterOffsetEnd":283,"pos":",","before":"","after":" "},{"index":52,"word":"if","originalText":"if","characterOffsetBegin":284,"characterOffsetEnd":286,"pos":"IN","before":" ","after":" "},{"index":53,"word":"not","originalText":"not","characterOffsetBegin":287,"characterOffsetEnd":290,"pos":"RB","before":" ","after":""},{"index":54,"word":">>","originalText":">>","characterOffsetBegin":290,"characterOffsetEnd":292,"pos":"CD","before":"","after":""},{"index":55,"word":"impossible","originalText":"impossible","characterOffsetBegin":292,"characterOffsetEnd":302,"pos":"JJ","before":"","after":""},{"index":56,"word":",","originalText":",","characterOffsetBegin":302,"characterOffsetEnd":303,"pos":",","before":"","after":" "},{"index":57,"word":"to","originalText":"to","characterOffsetBegin":304,"characterOffsetEnd":306,"pos":"TO","before":" ","after":" "},{"index":58,"word":"answer","originalText":"answer","characterOffsetBegin":307,"characterOffsetEnd":313,"pos":"VB","before":" ","after":""},{"index":59,"word":".","originalText":".","characterOffsetBegin":313,"characterOffsetEnd":314,"pos":".","before":"","after":"  "}]},{"index":1,"tokens":[{"index":1,"word":"What","originalText":"What","characterOffsetBegin":316,"characterOffsetEnd":320,"pos":"WDT","before":"  ","after":" "},{"index":2,"word":"exactly","originalText":"exactly","characterOffsetBegin":321,"characterOffsetEnd":328,"pos":"RB","before":" ","after":" "},{"index":3,"word":"do","originalText":"do","characterOffsetBegin":329,"characterOffsetEnd":331,"pos":"VBP","before":" ","after":" "},{"index":4,"word":"you","originalText":"you","characterOffsetBegin":332,"characterOffsetEnd":335,"pos":"PRP","before":" ","after":" "},{"index":5,"word":"want","originalText":"want","characterOffsetBegin":336,"characterOffsetEnd":340,"pos":"VB","before":" ","after":" "},{"index":6,"word":"to","originalText":"to","characterOffsetBegin":341,"characterOffsetEnd":343,"pos":"TO","before":" ","after":" "},{"index":7,"word":"know","originalText":"know","characterOffsetBegin":344,"characterOffsetEnd":348,"pos":"VB","before":" ","after":""},{"index":8,"word":"?","originalText":"?","characterOffsetBegin":348,"characterOffsetEnd":349,"pos":".","before":"","after":"  "}]},{"index":2,"tokens":[{"index":1,"word":"Do","originalText":"Do","characterOffsetBegin":351,"characterOffsetEnd":353,"pos":"VBP","before":"  ","after":" "},{"index":2,"word":"you","originalText":"you","characterOffsetBegin":354,"characterOffsetEnd":357,"pos":"PRP","before":" ","after":" "},{"index":3,"word":"need","originalText":"need","characterOffsetBegin":358,"characterOffsetEnd":362,"pos":"VB","before":" ","after":" "},{"index":4,"word":"a","originalText":"a","characterOffsetBegin":363,"characterOffsetEnd":364,"pos":"DT","before":" ","after":" "},{"index":5,"word":"good","originalText":"good","characterOffsetBegin":365,"characterOffsetEnd":369,"pos":"JJ","before":" ","after":""},{"index":6,"word":">>","originalText":">>","characterOffsetBegin":369,"characterOffsetEnd":371,"pos":"NN","before":"","after":""},{"index":7,"word":"one","originalText":"one","characterOffsetBegin":371,"characterOffsetEnd":374,"pos":"CD","before":"","after":" "},{"index":8,"word":"for","originalText":"for","characterOffsetBegin":375,"characterOffsetEnd":378,"pos":"IN","before":" ","after":" "},{"index":9,"word":"a","originalText":"a","characterOffsetBegin":379,"characterOffsetEnd":380,"pos":"DT","before":" ","after":" "},{"index":10,"word":"project","originalText":"project","characterOffsetBegin":381,"characterOffsetEnd":388,"pos":"NN","before":" ","after":" "},{"index":11,"word":"you","originalText":"you","characterOffsetBegin":389,"characterOffsetEnd":392,"pos":"PRP","before":" ","after":" "},{"index":12,"word":"are","originalText":"are","characterOffsetBegin":393,"characterOffsetEnd":396,"pos":"VBP","before":" ","after":" "},{"index":13,"word":"working","originalText":"working","characterOffsetBegin":397,"characterOffsetEnd":404,"pos":"VBG","before":" ","after":" "},{"index":14,"word":"on","originalText":"on","characterOffsetBegin":405,"characterOffsetEnd":407,"pos":"IN","before":" ","after":""},{"index":15,"word":"?","originalText":"?","characterOffsetBegin":407,"characterOffsetEnd":408,"pos":".","before":"","after":"  "}]},{"index":3,"tokens":[{"index":1,"word":"How","originalText":"How","characterOffsetBegin":410,"characterOffsetEnd":413,"pos":"WRB","before":"  ","after":" "},{"index":2,"word":"secure","originalText":"secure","characterOffsetBegin":414,"characterOffsetEnd":420,"pos":"JJ","before":" ","after":" "},{"index":3,"word":"must","originalText":"must","characterOffsetBegin":421,"characterOffsetEnd":425,"pos":"MD","before":" ","after":" "},{"index":4,"word":"it","originalText":"it","characterOffsetBegin":426,"characterOffsetEnd":428,"pos":"PRP","before":" ","after":" "},{"index":5,"word":"be","originalText":"be","characterOffsetBegin":429,"characterOffsetEnd":431,"pos":"VB","before":" ","after":""},{"index":6,"word":"?","originalText":"?","characterOffsetBegin":431,"characterOffsetEnd":432,"pos":".","before":"","after":"  "}]},{"index":4,"tokens":[{"index":1,"word":"Are","originalText":"Are","characterOffsetBegin":434,"characterOffsetEnd":437,"pos":"VBP","before":"  ","after":" "},{"index":2,"word":"you","originalText":"you","characterOffsetBegin":438,"characterOffsetEnd":441,"pos":"PRP","before":" ","after":" "},{"index":3,"word":"trying","originalText":"trying","characterOffsetBegin":442,"characterOffsetEnd":448,"pos":"VBG","before":" ","after":""},{"index":4,"word":">>","originalText":">>","characterOffsetBegin":448,"characterOffsetEnd":450,"pos":"CD","before":"","after":""},{"index":5,"word":"to","originalText":"to","characterOffsetBegin":450,"characterOffsetEnd":452,"pos":"TO","before":"","after":" "},{"index":6,"word":"crack","originalText":"crack","characterOffsetBegin":453,"characterOffsetEnd":458,"pos":"VB","before":" ","after":" "},{"index":7,"word":"one","originalText":"one","characterOffsetBegin":459,"characterOffsetEnd":462,"pos":"CD","before":" ","after":" "},{"index":8,"word":"that","originalText":"that","characterOffsetBegin":463,"characterOffsetEnd":467,"pos":"WDT","before":" ","after":" "},{"index":9,"word":"someone","originalText":"someone","characterOffsetBegin":468,"characterOffsetEnd":475,"pos":"NN","before":" ","after":" "},{"index":10,"word":"else","originalText":"else","characterOffsetBegin":476,"characterOffsetEnd":480,"pos":"RB","before":" ","after":" "},{"index":11,"word":"has","originalText":"has","characterOffsetBegin":481,"characterOffsetEnd":484,"pos":"VBZ","before":" ","after":" "},{"index":12,"word":"used","originalText":"used","characterOffsetBegin":485,"characterOffsetEnd":489,"pos":"VBN","before":" ","after":""},{"index":13,"word":"?","originalText":"?","characterOffsetBegin":489,"characterOffsetEnd":490,"pos":".","before":"","after":"  "}]},{"index":5,"tokens":[{"index":1,"word":"I","originalText":"I","characterOffsetBegin":492,"characterOffsetEnd":493,"pos":"PRP","before":"  ","after":" "},{"index":2,"word":"can","originalText":"can","characterOffsetBegin":494,"characterOffsetEnd":497,"pos":"MD","before":" ","after":" "},{"index":3,"word":"probably","originalText":"probably","characterOffsetBegin":498,"characterOffsetEnd":506,"pos":"RB","before":" ","after":" "},{"index":4,"word":"make","originalText":"make","characterOffsetBegin":507,"characterOffsetEnd":511,"pos":"VB","before":" ","after":" "},{"index":5,"word":"suggestions","originalText":"suggestions","characterOffsetBegin":512,"characterOffsetEnd":523,"pos":"NNS","before":" ","after":""},{"index":6,"word":",","originalText":",","characterOffsetBegin":523,"characterOffsetEnd":524,"pos":",","before":"","after":""},{"index":7,"word":">>","originalText":">>","characterOffsetBegin":524,"characterOffsetEnd":526,"pos":"NN","before":"","after":""},{"index":8,"word":"assuming","originalText":"assuming","characterOffsetBegin":526,"characterOffsetEnd":534,"pos":"VBG","before":"","after":" "},{"index":9,"word":"the","originalText":"the","characterOffsetBegin":535,"characterOffsetEnd":538,"pos":"DT","before":" ","after":" "},{"index":10,"word":"activity","originalText":"activity","characterOffsetBegin":539,"characterOffsetEnd":547,"pos":"NN","before":" ","after":" "},{"index":11,"word":"is","originalText":"is","characterOffsetBegin":548,"characterOffsetEnd":550,"pos":"VBZ","before":" ","after":" "},{"index":12,"word":"strictly","originalText":"strictly","characterOffsetBegin":551,"characterOffsetEnd":559,"pos":"RB","before":" ","after":" "},{"index":13,"word":"legal","originalText":"legal","characterOffsetBegin":560,"characterOffsetEnd":565,"pos":"JJ","before":" ","after":""},{"index":14,"word":".","originalText":".","characterOffsetBegin":565,"characterOffsetEnd":566,"pos":".","before":"","after":"  "}]},{"index":6,"tokens":[{"index":1,"word":"-LRB-","originalText":"(","characterOffsetBegin":568,"characterOffsetEnd":569,"pos":"-LRB-","before":"  ","after":""},{"index":2,"word":"In","originalText":"In","characterOffsetBegin":569,"characterOffsetEnd":571,"pos":"IN","before":"","after":" "},{"index":3,"word":"general","originalText":"general","characterOffsetBegin":572,"characterOffsetEnd":579,"pos":"JJ","before":" ","after":""},{"index":4,"word":",","originalText":",","characterOffsetBegin":579,"characterOffsetEnd":580,"pos":",","before":"","after":" "},{"index":5,"word":"it","originalText":"it","characterOffsetBegin":581,"characterOffsetEnd":583,"pos":"PRP","before":" ","after":" "},{"index":6,"word":"is","originalText":"is","characterOffsetBegin":584,"characterOffsetEnd":586,"pos":"VBZ","before":" ","after":" "},{"index":7,"word":"a","originalText":"a","characterOffsetBegin":587,"characterOffsetEnd":588,"pos":"DT","before":" ","after":" "},{"index":8,"word":"BAD","originalText":"BAD","characterOffsetBegin":589,"characterOffsetEnd":592,"pos":"JJ","before":" ","after":" "},{"index":9,"word":"idea","originalText":"idea","characterOffsetBegin":593,"characterOffsetEnd":597,"pos":"NN","before":" ","after":""},{"index":10,"word":",","originalText":",","characterOffsetBegin":597,"characterOffsetEnd":598,"pos":",","before":"","after":""},{"index":11,"word":">>","originalText":">>","characterOffsetBegin":598,"characterOffsetEnd":600,"pos":"CD","before":"","after":""},{"index":12,"word":"legally","originalText":"legally","characterOffsetBegin":600,"characterOffsetEnd":607,"pos":"RB","before":"","after":""},{"index":13,"word":",","originalText":",","characterOffsetBegin":607,"characterOffsetEnd":608,"pos":",","before":"","after":" "},{"index":14,"word":"to","originalText":"to","characterOffsetBegin":609,"characterOffsetEnd":611,"pos":"TO","before":" ","after":" "},{"index":15,"word":"tamper","originalText":"tamper","characterOffsetBegin":612,"characterOffsetEnd":618,"pos":"VB","before":" ","after":" "},{"index":16,"word":"with","originalText":"with","characterOffsetBegin":619,"characterOffsetEnd":623,"pos":"IN","before":" ","after":" "},{"index":17,"word":"copy","originalText":"copy","characterOffsetBegin":624,"characterOffsetEnd":628,"pos":"NN","before":" ","after":" "},{"index":18,"word":"protection","originalText":"protection","characterOffsetBegin":629,"characterOffsetEnd":639,"pos":"NN","before":" ","after":""},{"index":19,"word":".","originalText":".","characterOffsetBegin":639,"characterOffsetEnd":640,"pos":".","before":"","after":"  "}]},{"index":7,"tokens":[{"index":1,"word":"It","originalText":"It","characterOffsetBegin":642,"characterOffsetEnd":644,"pos":"PRP","before":"  ","after":" "},{"index":2,"word":"can","originalText":"can","characterOffsetBegin":645,"characterOffsetEnd":648,"pos":"MD","before":" ","after":" "},{"index":3,"word":"also","originalText":"also","characterOffsetBegin":649,"characterOffsetEnd":653,"pos":"RB","before":" ","after":" "},{"index":4,"word":"lead","originalText":"lead","characterOffsetBegin":654,"characterOffsetEnd":658,"pos":"VB","before":" ","after":" "},{"index":5,"word":"to","originalText":"to","characterOffsetBegin":659,"characterOffsetEnd":661,"pos":"TO","before":" ","after":" "},{"index":6,"word":"corruption","originalText":"corruption","characterOffsetBegin":662,"characterOffsetEnd":672,"pos":"NN","before":" ","after":" "},{"index":7,"word":"of","originalText":"of","characterOffsetBegin":673,"characterOffsetEnd":675,"pos":"IN","before":" ","after":""},{"index":8,"word":">>","originalText":">>","characterOffsetBegin":675,"characterOffsetEnd":677,"pos":"CD","before":"","after":""},{"index":9,"word":"files","originalText":"files","characterOffsetBegin":677,"characterOffsetEnd":682,"pos":"NNS","before":"","after":" "},{"index":10,"word":"which","originalText":"which","characterOffsetBegin":683,"characterOffsetEnd":688,"pos":"WDT","before":" ","after":" "},{"index":11,"word":"you","originalText":"you","characterOffsetBegin":689,"characterOffsetEnd":692,"pos":"PRP","before":" ","after":" "},{"index":12,"word":"necessarily","originalText":"necessarily","characterOffsetBegin":693,"characterOffsetEnd":704,"pos":"RB","before":" ","after":" "},{"index":13,"word":"do","originalText":"do","characterOffsetBegin":705,"characterOffsetEnd":707,"pos":"VBP","before":" ","after":" "},{"index":14,"word":"not","originalText":"not","characterOffsetBegin":708,"characterOffsetEnd":711,"pos":"RB","before":" ","after":" "},{"index":15,"word":"have","originalText":"have","characterOffsetBegin":712,"characterOffsetEnd":716,"pos":"VB","before":" ","after":" "},{"index":16,"word":"back","originalText":"back","characterOffsetBegin":717,"characterOffsetEnd":721,"pos":"RB","before":" ","after":" "},{"index":17,"word":"ups","originalText":"ups","characterOffsetBegin":722,"characterOffsetEnd":725,"pos":"NNS","before":" ","after":" "},{"index":18,"word":"of","originalText":"of","characterOffsetBegin":726,"characterOffsetEnd":728,"pos":"IN","before":" ","after":" "},{"index":19,"word":"-LRB-","originalText":"(","characterOffsetBegin":729,"characterOffsetEnd":730,"pos":"-LRB-","before":" ","after":""},{"index":20,"word":"being","originalText":"being","characterOffsetBegin":730,"characterOffsetEnd":735,"pos":"VBG","before":"","after":" "},{"index":21,"word":"as","originalText":"as","characterOffsetBegin":736,"characterOffsetEnd":738,"pos":"IN","before":" ","after":" "},{"index":22,"word":"they","originalText":"they","characterOffsetBegin":739,"characterOffsetEnd":743,"pos":"PRP","before":" ","after":" "},{"index":23,"word":"are","originalText":"are","characterOffsetBegin":744,"characterOffsetEnd":747,"pos":"VBP","before":" ","after":" "},{"index":24,"word":"copy","originalText":"copy","characterOffsetBegin":748,"characterOffsetEnd":752,"pos":"NN","before":" ","after":""},{"index":25,"word":">>","originalText":">>","characterOffsetBegin":752,"characterOffsetEnd":754,"pos":"NN","before":"","after":""},{"index":26,"word":"protected","originalText":"protected","characterOffsetBegin":754,"characterOffsetEnd":763,"pos":"VBD","before":"","after":""},{"index":27,"word":",","originalText":",","characterOffsetBegin":763,"characterOffsetEnd":764,"pos":",","before":"","after":""},{"index":28,"word":"-RRB-","originalText":")","characterOffsetBegin":764,"characterOffsetEnd":765,"pos":"-RRB-","before":"","after":" "},{"index":29,"word":"which","originalText":"which","characterOffsetBegin":766,"characterOffsetEnd":771,"pos":"WDT","before":" ","after":" "},{"index":30,"word":"can","originalText":"can","characterOffsetBegin":772,"characterOffsetEnd":775,"pos":"MD","before":" ","after":" "},{"index":31,"word":"be","originalText":"be","characterOffsetBegin":776,"characterOffsetEnd":778,"pos":"VB","before":" ","after":" "},{"index":32,"word":"devestating","originalText":"devestating","characterOffsetBegin":779,"characterOffsetEnd":790,"pos":"VBG","before":" ","after":""},{"index":33,"word":".","originalText":".","characterOffsetBegin":790,"characterOffsetEnd":791,"pos":".","before":"","after":""},{"index":34,"word":"-RRB-","originalText":")","characterOffsetBegin":791,"characterOffsetEnd":792,"pos":"-RRB-","before":"","after":"  "}]},{"index":8,"tokens":[{"index":1,"word":"Do","originalText":"Do","characterOffsetBegin":794,"characterOffsetEnd":796,"pos":"VB","before":"  ","after":" "},{"index":2,"word":"you","originalText":"you","characterOffsetBegin":797,"characterOffsetEnd":800,"pos":"PRP","before":" ","after":" "},{"index":3,"word":"have","originalText":"have","characterOffsetBegin":801,"characterOffsetEnd":805,"pos":"VBP","before":" ","after":" "},{"index":4,"word":"absolutely","originalText":"absolutely","characterOffsetBegin":806,"characterOffsetEnd":816,"pos":"RB","before":" ","after":" "},{"index":5,"word":"no","originalText":"no","characterOffsetBegin":817,"characterOffsetEnd":819,"pos":"DT","before":" ","after":" "},{"index":6,"word":"ideas","originalText":"ideas","characterOffsetBegin":820,"characterOffsetEnd":825,"pos":"NNS","before":" ","after":" "},{"index":7,"word":"for","originalText":"for","characterOffsetBegin":826,"characterOffsetEnd":829,"pos":"IN","before":" ","after":""},{"index":8,"word":">>","originalText":">>","characterOffsetBegin":829,"characterOffsetEnd":831,"pos":"CD","before":"","after":""},{"index":9,"word":"practical","originalText":"practical","characterOffsetBegin":831,"characterOffsetEnd":840,"pos":"JJ","before":"","after":" "},{"index":10,"word":"applications","originalText":"applications","characterOffsetBegin":841,"characterOffsetEnd":853,"pos":"NNS","before":" ","after":""},{"index":11,"word":",","originalText":",","characterOffsetBegin":853,"characterOffsetEnd":854,"pos":",","before":"","after":" "},{"index":12,"word":"and","originalText":"and","characterOffsetBegin":855,"characterOffsetEnd":858,"pos":"CC","before":" ","after":" "},{"index":13,"word":"are","originalText":"are","characterOffsetBegin":859,"characterOffsetEnd":862,"pos":"VBP","before":" ","after":" "},{"index":14,"word":"merely","originalText":"merely","characterOffsetBegin":863,"characterOffsetEnd":869,"pos":"RB","before":" ","after":" "},{"index":15,"word":"curious","originalText":"curious","characterOffsetBegin":870,"characterOffsetEnd":877,"pos":"JJ","before":" ","after":""},{"index":16,"word":"?","originalText":"?","characterOffsetBegin":877,"characterOffsetEnd":878,"pos":".","before":"","after":""}]},{"index":9,"tokens":[{"index":1,"word":">>","originalText":">>","characterOffsetBegin":878,"characterOffsetEnd":880,"pos":"NN","before":"","after":"\t"},{"index":2,"word":"Please","originalText":"Please","characterOffsetBegin":881,"characterOffsetEnd":887,"pos":"UH","before":"\t","after":" "},{"index":3,"word":"clear","originalText":"clear","characterOffsetBegin":888,"characterOffsetEnd":893,"pos":"VB","before":" ","after":" "},{"index":4,"word":"up","originalText":"up","characterOffsetBegin":894,"characterOffsetEnd":896,"pos":"RP","before":" ","after":" "},{"index":5,"word":"those","originalText":"those","characterOffsetBegin":897,"characterOffsetEnd":902,"pos":"DT","before":" ","after":" "},{"index":6,"word":"questions","originalText":"questions","characterOffsetBegin":903,"characterOffsetEnd":912,"pos":"NNS","before":" ","after":""},{"index":7,"word":",","originalText":",","characterOffsetBegin":912,"characterOffsetEnd":913,"pos":",","before":"","after":" "},{"index":8,"word":"and","originalText":"and","characterOffsetBegin":914,"characterOffsetEnd":917,"pos":"CC","before":" ","after":" "},{"index":9,"word":"I","originalText":"I","characterOffsetBegin":918,"characterOffsetEnd":919,"pos":"PRP","before":" ","after":""},{"index":10,"word":"'ll","originalText":"'ll","characterOffsetBegin":919,"characterOffsetEnd":922,"pos":"MD","before":"","after":" "},{"index":11,"word":"try","originalText":"try","characterOffsetBegin":923,"characterOffsetEnd":926,"pos":"VB","before":" ","after":" "},{"index":12,"word":"to","originalText":"to","characterOffsetBegin":927,"characterOffsetEnd":929,"pos":"TO","before":" ","after":" "},{"index":13,"word":"help","originalText":"help","characterOffsetBegin":930,"characterOffsetEnd":934,"pos":"VB","before":" ","after":" "},{"index":14,"word":"as","originalText":"as","characterOffsetBegin":935,"characterOffsetEnd":937,"pos":"RB","before":" ","after":" "},{"index":15,"word":"much","originalText":"much","characterOffsetBegin":938,"characterOffsetEnd":942,"pos":"JJ","before":" ","after":" "},{"index":16,"word":"as","originalText":"as","characterOffsetBegin":943,"characterOffsetEnd":945,"pos":"IN","before":" ","after":" "},{"index":17,"word":"I","originalText":"I","characterOffsetBegin":946,"characterOffsetEnd":947,"pos":"PRP","before":" ","after":""},{"index":18,"word":">>","originalText":">>","characterOffsetBegin":947,"characterOffsetEnd":949,"pos":"VBP","before":"","after":""},{"index":19,"word":"can","originalText":"can","characterOffsetBegin":949,"characterOffsetEnd":952,"pos":"MD","before":"","after":""},{"index":20,"word":".","originalText":".","characterOffsetBegin":952,"characterOffsetEnd":953,"pos":".","before":"","after":""},{"index":21,"word":">","originalText":">","characterOffsetBegin":953,"characterOffsetEnd":954,"pos":"JJR","before":"","after":""}]},{"index":10,"tokens":[{"index":1,"word":"May","originalText":"May","characterOffsetBegin":954,"characterOffsetEnd":957,"pos":"NNP","before":"","after":" "},{"index":2,"word":"we","originalText":"we","characterOffsetBegin":958,"characterOffsetEnd":960,"pos":"PRP","before":" ","after":" "},{"index":3,"word":"interpret","originalText":"interpret","characterOffsetBegin":961,"characterOffsetEnd":970,"pos":"VB","before":" ","after":" "},{"index":4,"word":"this","originalText":"this","characterOffsetBegin":971,"characterOffsetEnd":975,"pos":"DT","before":" ","after":" "},{"index":5,"word":"as","originalText":"as","characterOffsetBegin":976,"characterOffsetEnd":978,"pos":"IN","before":" ","after":" "},{"index":6,"word":"an","originalText":"an","characterOffsetBegin":979,"characterOffsetEnd":981,"pos":"DT","before":" ","after":" "},{"index":7,"word":"offer","originalText":"offer","characterOffsetBegin":982,"characterOffsetEnd":987,"pos":"NN","before":" ","after":" "},{"index":8,"word":"to","originalText":"to","characterOffsetBegin":988,"characterOffsetEnd":990,"pos":"TO","before":" ","after":" "},{"index":9,"word":"volunteer","originalText":"volunteer","characterOffsetBegin":991,"characterOffsetEnd":1000,"pos":"NN","before":" ","after":" "},{"index":10,"word":"as","originalText":"as","characterOffsetBegin":1001,"characterOffsetEnd":1003,"pos":"IN","before":" ","after":" "},{"index":11,"word":"editor","originalText":"editor","characterOffsetBegin":1004,"characterOffsetEnd":1010,"pos":"NN","before":" ","after":" "},{"index":12,"word":"for","originalText":"for","characterOffsetBegin":1011,"characterOffsetEnd":1014,"pos":"IN","before":" ","after":" "},{"index":13,"word":"a","originalText":"a","characterOffsetBegin":1015,"characterOffsetEnd":1016,"pos":"DT","before":" ","after":""},{"index":14,"word":">","originalText":">","characterOffsetBegin":1016,"characterOffsetEnd":1017,"pos":"JJR","before":"","after":""},{"index":15,"word":"``","originalText":"\"","characterOffsetBegin":1017,"characterOffsetEnd":1018,"pos":"``","before":"","after":""},{"index":16,"word":"Copy","originalText":"Copy","characterOffsetBegin":1018,"characterOffsetEnd":1022,"pos":"VB","before":"","after":" "},{"index":17,"word":"protection","originalText":"protection","characterOffsetBegin":1023,"characterOffsetEnd":1033,"pos":"NN","before":" ","after":" "},{"index":18,"word":"FAQ","originalText":"FAQ","characterOffsetBegin":1034,"characterOffsetEnd":1037,"pos":"NN","before":" ","after":""},{"index":19,"word":"''","originalText":"\"","characterOffsetBegin":1037,"characterOffsetEnd":1038,"pos":"''","before":"","after":" "},{"index":20,"word":"?","originalText":"?","characterOffsetBegin":1039,"characterOffsetEnd":1040,"pos":".","before":" ","after":" "}]},{"index":11,"tokens":[{"index":1,"word":"I","originalText":"I","characterOffsetBegin":1041,"characterOffsetEnd":1042,"pos":"PRP","before":" ","after":" "},{"index":2,"word":"am","originalText":"am","characterOffsetBegin":1043,"characterOffsetEnd":1045,"pos":"VBP","before":" ","after":" "},{"index":3,"word":"quite","originalText":"quite","characterOffsetBegin":1046,"characterOffsetEnd":1051,"pos":"RB","before":" ","after":" "},{"index":4,"word":"sure","originalText":"sure","characterOffsetBegin":1052,"characterOffsetEnd":1056,"pos":"JJ","before":" ","after":" "},{"index":5,"word":"that","originalText":"that","characterOffsetBegin":1057,"characterOffsetEnd":1061,"pos":"IN","before":" ","after":" "},{"index":6,"word":"I","originalText":"I","characterOffsetBegin":1062,"characterOffsetEnd":1063,"pos":"PRP","before":" ","after":" "},{"index":7,"word":"am","originalText":"am","characterOffsetBegin":1064,"characterOffsetEnd":1066,"pos":"VBP","before":" ","after":" "},{"index":8,"word":"not","originalText":"not","characterOffsetBegin":1067,"characterOffsetEnd":1070,"pos":"RB","before":" ","after":" "},{"index":9,"word":"alone","originalText":"alone","characterOffsetBegin":1071,"characterOffsetEnd":1076,"pos":"RB","before":" ","after":" "},{"index":10,"word":"welcoming","originalText":"welcoming","characterOffsetBegin":1077,"characterOffsetEnd":1086,"pos":"VBG","before":" ","after":" "},{"index":11,"word":"such","originalText":"such","characterOffsetBegin":1087,"characterOffsetEnd":1091,"pos":"JJ","before":" ","after":""},{"index":12,"word":">","originalText":">","characterOffsetBegin":1091,"characterOffsetEnd":1092,"pos":"JJR","before":"","after":""},{"index":13,"word":"an","originalText":"an","characterOffsetBegin":1092,"characterOffsetEnd":1094,"pos":"DT","before":"","after":" "},{"index":14,"word":"initiative","originalText":"initiative","characterOffsetBegin":1095,"characterOffsetEnd":1105,"pos":"NN","before":" ","after":""},{"index":15,"word":"!","originalText":"!","characterOffsetBegin":1105,"characterOffsetEnd":1106,"pos":".","before":"","after":" "}]},{"index":12,"tokens":[{"index":1,"word":"*","originalText":"*","characterOffsetBegin":1107,"characterOffsetEnd":1108,"pos":"SYM","before":" ","after":""},{"index":2,"word":"I","originalText":"I","characterOffsetBegin":1108,"characterOffsetEnd":1109,"pos":"PRP","before":"","after":""},{"index":3,"word":"*","originalText":"*","characterOffsetBegin":1109,"characterOffsetEnd":1110,"pos":"SYM","before":"","after":" "},{"index":4,"word":"will","originalText":"will","characterOffsetBegin":1111,"characterOffsetEnd":1115,"pos":"MD","before":" ","after":" "},{"index":5,"word":"volunteer","originalText":"volunteer","characterOffsetBegin":1116,"characterOffsetEnd":1125,"pos":"VB","before":" ","after":" "},{"index":6,"word":"to","originalText":"to","characterOffsetBegin":1126,"characterOffsetEnd":1128,"pos":"TO","before":" ","after":" "},{"index":7,"word":"ask","originalText":"ask","characterOffsetBegin":1129,"characterOffsetEnd":1132,"pos":"VB","before":" ","after":" "},{"index":8,"word":"some","originalText":"some","characterOffsetBegin":1133,"characterOffsetEnd":1137,"pos":"DT","before":" ","after":" "},{"index":9,"word":"of","originalText":"of","characterOffsetBegin":1138,"characterOffsetEnd":1140,"pos":"IN","before":" ","after":" "},{"index":10,"word":"the","originalText":"the","characterOffsetBegin":1141,"characterOffsetEnd":1144,"pos":"DT","before":" ","after":" "},{"index":11,"word":"questions","originalText":"questions","characterOffsetBegin":1145,"characterOffsetEnd":1154,"pos":"NNS","before":" ","after":""},{"index":12,"word":",","originalText":",","characterOffsetBegin":1154,"characterOffsetEnd":1155,"pos":",","before":"","after":" "},{"index":13,"word":"if","originalText":"if","characterOffsetBegin":1156,"characterOffsetEnd":1158,"pos":"IN","before":" ","after":" "},{"index":14,"word":"you","originalText":"you","characterOffsetBegin":1159,"characterOffsetEnd":1162,"pos":"PRP","before":" ","after":" "},{"index":15,"word":"will","originalText":"will","characterOffsetBegin":1163,"characterOffsetEnd":1167,"pos":"MD","before":" ","after":""},{"index":16,"word":">","originalText":">","characterOffsetBegin":1167,"characterOffsetEnd":1168,"pos":"RBR","before":"","after":""},{"index":17,"word":"provide","originalText":"provide","characterOffsetBegin":1168,"characterOffsetEnd":1175,"pos":"VB","before":"","after":" "},{"index":18,"word":"the","originalText":"the","characterOffsetBegin":1176,"characterOffsetEnd":1179,"pos":"DT","before":" ","after":" "},{"index":19,"word":"answers","originalText":"answers","characterOffsetBegin":1180,"characterOffsetEnd":1187,"pos":"NNS","before":" ","after":" "},{"index":20,"word":":--RRB-","originalText":":-)","characterOffsetBegin":1188,"characterOffsetEnd":1191,"pos":"JJ","before":" ","after":""},{"index":21,"word":">","originalText":">","characterOffsetBegin":1191,"characterOffsetEnd":1192,"pos":"JJR","before":"","after":""},{"index":22,"word":"Ketil","originalText":"Ketil","characterOffsetBegin":1192,"characterOffsetEnd":1197,"pos":"NNP","before":"","after":" "},{"index":23,"word":"AlbertsenThat","originalText":"AlbertsenThat","characterOffsetBegin":1198,"characterOffsetEnd":1211,"pos":"NNP","before":" ","after":""},{"index":24,"word":"'s","originalText":"'s","characterOffsetBegin":1211,"characterOffsetEnd":1213,"pos":"POS","before":"","after":" "},{"index":25,"word":"great","originalText":"great","characterOffsetBegin":1214,"characterOffsetEnd":1219,"pos":"JJ","before":" ","after":""},{"index":26,"word":".","originalText":".","characterOffsetBegin":1219,"characterOffsetEnd":1220,"pos":".","before":"","after":"  "}]},{"index":13,"tokens":[{"index":1,"word":"Read","originalText":"Read","characterOffsetBegin":1222,"characterOffsetEnd":1226,"pos":"VB","before":"  ","after":" "},{"index":2,"word":"my","originalText":"my","characterOffsetBegin":1227,"characterOffsetEnd":1229,"pos":"PRP$","before":" ","after":" "},{"index":3,"word":"article","originalText":"article","characterOffsetBegin":1230,"characterOffsetEnd":1237,"pos":"NN","before":" ","after":""},{"index":4,"word":".","originalText":".","characterOffsetBegin":1237,"characterOffsetEnd":1238,"pos":".","before":"","after":"  "}]},{"index":14,"tokens":[{"index":1,"word":"Edit","originalText":"Edit","characterOffsetBegin":1240,"characterOffsetEnd":1244,"pos":"VB","before":"  ","after":" "},{"index":2,"word":"out","originalText":"out","characterOffsetBegin":1245,"characterOffsetEnd":1248,"pos":"RP","before":" ","after":" "},{"index":3,"word":"the","originalText":"the","characterOffsetBegin":1249,"characterOffsetEnd":1252,"pos":"DT","before":" ","after":" "},{"index":4,"word":"personal","originalText":"personal","characterOffsetBegin":1253,"characterOffsetEnd":1261,"pos":"JJ","before":" ","after":" "},{"index":5,"word":"formality","originalText":"formality","characterOffsetBegin":1262,"characterOffsetEnd":1271,"pos":"NN","before":" ","after":""},{"index":6,"word":",","originalText":",","characterOffsetBegin":1271,"characterOffsetEnd":1272,"pos":",","before":"","after":" "},{"index":7,"word":"and","originalText":"and","characterOffsetBegin":1273,"characterOffsetEnd":1276,"pos":"CC","before":" ","after":" "},{"index":8,"word":"save","originalText":"save","characterOffsetBegin":1277,"characterOffsetEnd":1281,"pos":"VB","before":" ","after":""},{"index":9,"word":".","originalText":".","characterOffsetBegin":1281,"characterOffsetEnd":1282,"pos":".","before":"","after":""}]},{"index":15,"tokens":[{"index":1,"word":"---------------------------------------------------------------------------------","originalText":"---------------------------------------------------------------------------------","characterOffsetBegin":1282,"characterOffsetEnd":1363,"pos":"CD","before":"","after":""},{"index":2,"word":"George","originalText":"George","characterOffsetBegin":1363,"characterOffsetEnd":1369,"pos":"NNP","before":"","after":" "},{"index":3,"word":"Gruschow","originalText":"Gruschow","characterOffsetBegin":1370,"characterOffsetEnd":1378,"pos":"NNP","before":" ","after":"                                "},{"index":4,"word":"Death","originalText":"Death","characterOffsetBegin":1410,"characterOffsetEnd":1415,"pos":"NNP","before":"                                ","after":" "},{"index":5,"word":"do","originalText":"do","characterOffsetBegin":1416,"characterOffsetEnd":1418,"pos":"VBP","before":" ","after":" "},{"index":6,"word":"you","originalText":"you","characterOffsetBegin":1419,"characterOffsetEnd":1422,"pos":"PRP","before":" ","after":" "},{"index":7,"word":"gronk.ag625@yfn.ysu.edu","originalText":"gronk.ag625@yfn.ysu.edu","characterOffsetBegin":1423,"characterOffsetEnd":1446,"pos":"FW","before":" ","after":"                              "},{"index":8,"word":"ggruscho@nyx.cs.du.edu-------------------------------------------------------------------------------","originalText":"ggruscho@nyx.cs.du.edu-------------------------------------------------------------------------------","characterOffsetBegin":1476,"characterOffsetEnd":1577,"pos":"FW","before":"                              ","after":""}]}]}